[
  {
    "Title": "Let Us Now Praise Famous Men",
    "Author": "Trujillo, Hadassah Y.",
    "Genre": "Non-fiction",
    "AmountInStock": 8
  },
  {
    "Title": "Moab Is My Washpot",
    "Author": "Ellison, Madaline U.",
    "Genre": "Adult",
    "AmountInStock": 45
  },
  {
    "Title": "In Death Ground",
    "Author": "Hopper, Piper A.",
    "Genre": "Adult",
    "AmountInStock": 2
  },
  {
    "Title": "The Millstone",
    "Author": "Gill, Leila H.",
    "Genre": "Sci-Fi",
    "AmountInStock": 2
  },
  {
    "Title": "To Your Scattered Bodies Go",
    "Author": "Holt, Gray X.",
    "Genre": "Comic",
    "AmountInStock": 2
  },
  {
    "Title": "Down to a Sunless Sea",
    "Author": "Sims, Matthew S.",
    "Genre": "Drama",
    "AmountInStock": 1
  },
  {
    "Title": "A Passage to India",
    "Author": "Herring, Pearl A.",
    "Genre": "Non-fiction",
    "AmountInStock": 7
  },
  {
    "Title": "Pale Kings and Princes",
    "Author": "Castaneda, Gemma T.",
    "Genre": "Romance",
    "AmountInStock": 8
  },
  {
    "Title": "The Mirror Crack'd from Side to Side",
    "Author": "Forbes, Rajah O.",
    "Genre": "Adventure",
    "AmountInStock": 5
  },
  {
    "Title": "The Man Within",
    "Author": "Macias, Claire H.",
    "Genre": "Sci-Fi",
    "AmountInStock": 4
  },
  {
    "Title": "In Dubious Battle",
    "Author": "Massey, Brady L.",
    "Genre": "Drama",
    "AmountInStock": 4
  },
  {
    "Title": "Blithe Spirit",
    "Author": "Delaney, Lacota U.",
    "Genre": "Thriller",
    "AmountInStock": 6
  },
  {
    "Title": "The Glory and the Dream",
    "Author": "Gill, Elton M.",
    "Genre": "Drama",
    "AmountInStock": 5
  },
  {
    "Title": "Blue Remembered Hills",
    "Author": "Mays, Macaulay D.",
    "Genre": "Romance",
    "AmountInStock": 1
  }
]